{
    "catppuccin-fcitx5": {
        "cargoLocks": null,
        "date": "2022-10-05",
        "extract": null,
        "name": "catppuccin-fcitx5",
        "passthru": null,
        "pinned": false,
        "src": {
            "deepClone": false,
            "fetchSubmodules": false,
            "leaveDotGit": false,
            "name": null,
            "owner": "catppuccin",
            "repo": "fcitx5",
            "rev": "ce244cfdf43a648d984719fdfd1d60aab09f5c97",
            "sha256": "sha256-uFaCbyrEjv4oiKUzLVFzw+UY54/h7wh2cntqeyYwGps=",
            "type": "github"
        },
        "version": "ce244cfdf43a648d984719fdfd1d60aab09f5c97"
    },
    "catppuccin-fish": {
        "cargoLocks": null,
        "date": "2023-11-02",
        "extract": null,
        "name": "catppuccin-fish",
        "passthru": null,
        "pinned": false,
        "src": {
            "deepClone": false,
            "fetchSubmodules": false,
            "leaveDotGit": false,
            "name": null,
            "owner": "catppuccin",
            "repo": "fish",
            "rev": "0ce27b518e8ead555dec34dd8be3df5bd75cff8e",
            "sha256": "sha256-Dc/zdxfzAUM5NX8PxzfljRbYvO9f9syuLO8yBr+R3qg=",
            "type": "github"
        },
        "version": "0ce27b518e8ead555dec34dd8be3df5bd75cff8e"
    },
    "fcitx5-pinyin-moegirl": {
        "cargoLocks": null,
        "date": null,
        "extract": null,
        "name": "fcitx5-pinyin-moegirl",
        "passthru": null,
        "pinned": false,
        "src": {
            "name": null,
            "sha256": "sha256-x+XkATiNMNbcSiN87MkRRvKiNuzvpmkDrtGkwdnIsYM=",
            "type": "url",
            "url": "https://github.com/outloudvi/mw2fcitx/releases/download/20231114/moegirl.dict"
        },
        "version": "20231114"
    },
    "fcitx5-pinyin-zhwiki": {
        "cargoLocks": null,
        "date": null,
        "extract": null,
        "name": "fcitx5-pinyin-zhwiki",
        "passthru": null,
        "pinned": false,
        "src": {
            "name": null,
            "sha256": "sha256-crMmSqQ7QgmjgEG8QpvBgQYfvttCUsKYo8gHZGXIZmc=",
            "type": "url",
            "url": "https://github.com/felixonmars/fcitx5-pinyin-zhwiki/releases/download/0.2.4/zhwiki-20231205.dict"
        },
        "version": "20231205"
    },
    "librime-lua": {
        "cargoLocks": null,
        "date": "2023-10-29",
        "extract": null,
        "name": "librime-lua",
        "passthru": null,
        "pinned": false,
        "src": {
            "deepClone": false,
            "fetchSubmodules": false,
            "leaveDotGit": false,
            "name": null,
            "owner": "hchunhui",
            "repo": "librime-lua",
            "rev": "7c297e4d2e08fcdd3e9b2dcae2a42317b9a217ff",
            "sha256": "sha256-GVfr2fzaQYyfNnjN20YcNfBVB144gZKVEunbX10Mgeg=",
            "type": "github"
        },
        "version": "7c297e4d2e08fcdd3e9b2dcae2a42317b9a217ff"
    },
    "overskride": {
        "cargoLocks": null,
        "date": "2023-11-20",
        "extract": {
            "Cargo.lock": "./overskride-73806b9949400fc3fb8e818c0341a560a4168f4d/Cargo.lock"
        },
        "name": "overskride",
        "passthru": null,
        "pinned": false,
        "src": {
            "deepClone": false,
            "fetchSubmodules": false,
            "leaveDotGit": false,
            "name": null,
            "owner": "kaii-lb",
            "repo": "overskride",
            "rev": "73806b9949400fc3fb8e818c0341a560a4168f4d",
            "sha256": "sha256-rYM5zdqrJd8FaPfV9Nn6TDQW9y16HSM4eIRi+JtuYFo=",
            "type": "github"
        },
        "version": "73806b9949400fc3fb8e818c0341a560a4168f4d"
    },
    "rime-ice": {
        "cargoLocks": null,
        "date": "2023-12-13",
        "extract": null,
        "name": "rime-ice",
        "passthru": null,
        "pinned": false,
        "src": {
            "deepClone": false,
            "fetchSubmodules": false,
            "leaveDotGit": false,
            "name": null,
            "owner": "iDvel",
            "repo": "rime-ice",
            "rev": "c9555ed3c09b3224eb7162047b92ffe744c902b8",
            "sha256": "sha256-y2md5i9TJX1BmtQJCB5/HAyLKiViRjJ9mS2onrhEXI8=",
            "type": "github"
        },
        "version": "c9555ed3c09b3224eb7162047b92ffe744c902b8"
    }
}